verifyreq/__init__.py
verifyreq/__main__.py
verifyreq/cli.py
verifyreq/version.py
verifyreq-0.1.1.dist-info/DESCRIPTION.rst
verifyreq-0.1.1.dist-info/METADATA
verifyreq-0.1.1.dist-info/RECORD
verifyreq-0.1.1.dist-info/WHEEL
verifyreq-0.1.1.dist-info/entry_points.txt
verifyreq-0.1.1.dist-info/metadata.json
verifyreq-0.1.1.dist-info/top_level.txt
