Metadata-Version: 2.0
Name: verifyreq
Version: 0.1.1
Summary: Tool to verify requirement file installations.
Home-page: https://github.com/gwax/verifyreq
Author: George Leslie-Waksman
Author-email: waksman@gmail.com
License: MIT
Keywords: distutils setuptools egg pip requirements
Platform: any
Classifier: Development Status :: 5 - Production/Stable
Classifier: Intended Audience :: Developers
Classifier: License :: OSI Approved :: MIT License
Classifier: Programming Language :: Python :: 2
Classifier: Programming Language :: Python :: 2.7
Classifier: Programming Language :: Python :: 3
Classifier: Programming Language :: Python :: 3.3
Classifier: Programming Language :: Python :: 3.4
Classifier: Programming Language :: Python :: 3.5
Classifier: Programming Language :: Python :: 3.6
Classifier: Programming Language :: Python :: Implementation :: PyPy
Classifier: Topic :: Software Development :: Build Tools
